src/__init__.py
src/collaborator.py
src/constants.py
ywh_collab-1.0.1.dist-info/LICENSE
ywh_collab-1.0.1.dist-info/METADATA
ywh_collab-1.0.1.dist-info/WHEEL
ywh_collab-1.0.1.dist-info/top_level.txt
ywh_collab-1.0.1.dist-info/RECORD
