Metadata-Version: 2.1
Name: ywh-collab
Version: 1.0.1
Summary: Yes We Hack private program comparator for hunters collaboration by Aethlios.
Home-page: https://github.com/AethliosIK/ywh-collab
Author: Aethios
Author-email: tom.chambaretaud@protonmail.com
License: Apache
Classifier: Programming Language :: Python
Classifier: Programming Language :: Python :: 3.9
License-File: LICENSE
Requires-Dist: requests
